lg/__init__.py
lg/cli.py
lg/engine.py
lg/jsonic.py
lg/protocol.py
lg/run_context.py
lg/scaffold.py
lg/section_processor.py
lg/types.py
lg/version.py
lg/_skeletons/__init__.py
lg/_skeletons/advanced/common.ctx.md
lg/_skeletons/advanced/sections.yaml
lg/_skeletons/advanced/agent/footer.tpl.md
lg/_skeletons/advanced/agent/index.tpl.md
lg/_skeletons/advanced/agent/listing-generator.md
lg/_skeletons/advanced/agent/pipeline.md
lg/_skeletons/advanced/agent/software-design.md
lg/_skeletons/advanced/agent/stack-(your-development-stack).md
lg/_skeletons/advanced/agent/workspace-and-personal.md
lg/_skeletons/basic/common.ctx.md
lg/_skeletons/basic/sections.yaml
lg/adapters/__init__.py
lg/adapters/base.py
lg/adapters/budget.py
lg/adapters/code_base.py
lg/adapters/code_model.py
lg/adapters/comment_style.py
lg/adapters/context.py
lg/adapters/markdown.py
lg/adapters/metrics.py
lg/adapters/placeholders.py
lg/adapters/processor.py
lg/adapters/range_edits.py
lg/adapters/registry.py
lg/adapters/tree_sitter_support.py
lg/adapters/langs/__init__.py
lg/adapters/langs/c/__init__.py
lg/adapters/langs/c/adapter.py
lg/adapters/langs/c/code_profiles.py
lg/adapters/langs/c/imports.py
lg/adapters/langs/c/literals.py
lg/adapters/langs/c/trivial.py
lg/adapters/langs/cpp/__init__.py
lg/adapters/langs/cpp/adapter.py
lg/adapters/langs/cpp/code_profiles.py
lg/adapters/langs/cpp/imports.py
lg/adapters/langs/cpp/literals.py
lg/adapters/langs/cpp/literals_component.py
lg/adapters/langs/cpp/trivial.py
lg/adapters/langs/go/__init__.py
lg/adapters/langs/go/adapter.py
lg/adapters/langs/go/code_profiles.py
lg/adapters/langs/go/comments.py
lg/adapters/langs/go/imports.py
lg/adapters/langs/go/literals.py
lg/adapters/langs/go/trivial.py
lg/adapters/langs/java/__init__.py
lg/adapters/langs/java/adapter.py
lg/adapters/langs/java/code_profiles.py
lg/adapters/langs/java/comments.py
lg/adapters/langs/java/imports.py
lg/adapters/langs/java/literals.py
lg/adapters/langs/java/literals_component.py
listing_generator-0.10.2.dist-info/licenses/LICENSE
listing_generator-0.10.2.dist-info/METADATA
listing_generator-0.10.2.dist-info/WHEEL
listing_generator-0.10.2.dist-info/entry_points.txt
listing_generator-0.10.2.dist-info/top_level.txt
listing_generator-0.10.2.dist-info/RECORD
