Metadata-Version: 2.4
Name: listing-generator
Version: 0.10.2
Summary: Plain-text source listing generator for AI context
Author-email: Maxim Morozov <mmocentre@gmail.com>
License: Apache License
Project-URL: Homepage, https://github.com/Max-Moro/lg-cli
Project-URL: Source, https://github.com/Max-Moro/lg-cli
Project-URL: Issues, https://github.com/Max-Moro/lg-cli/issues
Classifier: License :: OSI Approved :: Apache Software License
Classifier: Programming Language :: Python :: 3
Classifier: Programming Language :: Python :: 3.10
Requires-Python: >=3.10
License-File: LICENSE
Requires-Dist: ruamel.yaml>=0.18
Requires-Dist: pathspec>=0.12
Requires-Dist: tiktoken>=0.6
Requires-Dist: tokenizers>=0.15
Requires-Dist: sentencepiece>=0.2
Requires-Dist: huggingface-hub>=0.20
Requires-Dist: pydantic<3.0,>=2.0
Requires-Dist: tree-sitter>=0.21
Requires-Dist: tree-sitter-python>=0.23
Requires-Dist: tree-sitter-typescript>=0.23
Requires-Dist: tree-sitter-javascript>=0.25
Requires-Dist: tree-sitter-kotlin>=1.1.0
Requires-Dist: tree-sitter-java>=0.23
Requires-Dist: tree-sitter-cpp>=0.23
Requires-Dist: tree-sitter-c>=0.23
Requires-Dist: tree-sitter-scala>=0.23
Requires-Dist: tree-sitter-go>=0.23
Requires-Dist: tree-sitter-rust>=0.23
Provides-Extra: dev
Requires-Dist: pytest>=8.0; extra == "dev"
Requires-Dist: datamodel-code-generator>=0.25; extra == "dev"
Requires-Dist: vulture>=2.14; extra == "dev"
Requires-Dist: tomli>=2.0; python_version < "3.11" and extra == "dev"
Dynamic: license-file
